djangocms_blog_view_restrictions/__init__.py
djangocms_blog_view_restrictions/admin.py
djangocms_blog_view_restrictions/apps.py
djangocms_blog_view_restrictions/models.py
djangocms_blog_view_restrictions/conf/__init__.py
djangocms_blog_view_restrictions/conf/settings.py
djangocms_blog_view_restrictions/locale/fr/LC_MESSAGES/django.mo
djangocms_blog_view_restrictions/locale/fr/LC_MESSAGES/django.po
djangocms_blog_view_restrictions/migrations/0001_initial.py
djangocms_blog_view_restrictions/migrations/__init__.py
djangocms_blog_view_restrictions/templatetags/__init__.py
djangocms_blog_view_restrictions/templatetags/blog_view_restrictions_tags.py
djangocms_blog_view_restrictions-0.3.0.dist-info/AUTHORS.md
djangocms_blog_view_restrictions-0.3.0.dist-info/LICENSE
djangocms_blog_view_restrictions-0.3.0.dist-info/METADATA
djangocms_blog_view_restrictions-0.3.0.dist-info/WHEEL
djangocms_blog_view_restrictions-0.3.0.dist-info/top_level.txt
djangocms_blog_view_restrictions-0.3.0.dist-info/RECORD
