Metadata-Version: 2.1
Name: djangocms-blog-view-restrictions
Version: 0.3.0
Summary: Control who can view your djangocms-blog posts
Home-page: https://gitlab.com/kapt/open-source/djangocms-blog-view-restrictions
Author: Adrien Delhorme
Author-email: dev@kapt.mobi
Classifier: Environment :: Web Environment
Classifier: Framework :: Django
Classifier: Framework :: Django CMS
Classifier: Intended Audience :: Developers
Classifier: License :: OSI Approved :: GNU General Public License v3 (GPLv3)
Classifier: Programming Language :: Python
Classifier: Programming Language :: Python :: 3
Classifier: Topic :: Internet :: WWW/HTTP
Classifier: Topic :: Internet :: WWW/HTTP :: Dynamic Content
License-File: LICENSE
License-File: AUTHORS.md
Requires-Dist: djangocms-blog
